QianghuaXuexiZaiAliDeJishuYanjinYuYewuChuangxinFix1/README.md
QianghuaXuexiZaiAliDeJishuYanjinYuYewuChuangxinFix1/__init__.py
QianghuaXuexiZaiAliDeJishuYanjinYuYewuChuangxinFix1/__main__.py
QianghuaXuexiZaiAliDeJishuYanjinYuYewuChuangxinFix1/file.pdf
QianghuaXuexiZaiAliDeJishuYanjinYuYewuChuangxinFix1/index.html
qianghua_xuexi_zai_ali_de_jishu_yanjin_yu_yewu_chuangxin_fix1-2025.3.25.0.dist-info/METADATA
qianghua_xuexi_zai_ali_de_jishu_yanjin_yu_yewu_chuangxin_fix1-2025.3.25.0.dist-info/WHEEL
qianghua_xuexi_zai_ali_de_jishu_yanjin_yu_yewu_chuangxin_fix1-2025.3.25.0.dist-info/entry_points.txt
qianghua_xuexi_zai_ali_de_jishu_yanjin_yu_yewu_chuangxin_fix1-2025.3.25.0.dist-info/top_level.txt
qianghua_xuexi_zai_ali_de_jishu_yanjin_yu_yewu_chuangxin_fix1-2025.3.25.0.dist-info/RECORD
